hiurlparser/__init__.py
hiurlparser/public_suffix_list.dat
hiurlparser/public_suffix_list.py
hi_urlparser-3.0.4.dist-info/LICENSE
hi_urlparser-3.0.4.dist-info/METADATA
hi_urlparser-3.0.4.dist-info/WHEEL
hi_urlparser-3.0.4.dist-info/top_level.txt
hi_urlparser-3.0.4.dist-info/RECORD
